{
 "summary": "本集節目中，主持人謝孟恭分享了錢包與遙控器離奇出現的趣事，並探討了近期台積電海外布局損益、關稅戰局勢、聯準會降息預期、AWS 資本支出傳聞以及特斯拉最新財報。他指出，台積電美國廠初期虧損為正常折舊現象，而關稅戰在貝森特等溫和派發言下有收斂跡象。對於聯準會，他認為降息勢在必行，並分析了川普與鮑威爾的互動。此外，他釐清了 AWS 砍單傳聞，並對特斯拉財報後大漲、馬斯克回歸公司、Model Y 改款及機器人晶片規劃給予正面評價，建議在空頭市場中仍需注意高估值股票的風險。",
 "topics": [
  "生活趣事：錢包與遙控器離奇現身",
  "台積電海外布局損益與折舊政策解析",
  "美中關稅戰局勢與溫和派官員發言影響",
  "聯準會降息預期與川普的政治墊背策略",
  "AWS 砍單與 CoWoS 下調傳聞釐清",
  "特斯拉財報解析：馬斯克回歸、Model Y 改款與機器人晶片規劃",
  "空頭市場下的資產配置與高估值股票風險"
 ],
 "market_view": "市場目前已進入定義上的空頭市場，行情偏空，建議避開估值極高且短期內無法看到大量獲利灌入的公司。",
 "industries": [
  {
   "name": "半導體",
   "stance": "看多",
   "view": "台積電等優質半導體公司在空頭市場中估值已跌至非常便宜且具吸引力的水準。"
  },
  {
   "name": "AI伺服器",
   "stance": "觀察",
   "view": "微軟確實有放緩資本支出，但 AWS 與 Google 整體需求依然健康，CoWoS 下調可能僅是產品換代調整。"
  },
  {
   "name": "電動車",
   "stance": "觀察",
   "view": "特斯拉短期交車數據下滑主因 Model Y 改款過渡期，長期仍需觀察機器人與軟體服務的變現進度。"
  }
 ],
 "tickers": [
  {
   "symbol": "2330",
   "name": "台積電",
   "market": "TW",
   "stance": "看多",
   "argument": "海外建廠初期虧損為五年快速折舊的正常現象，目前估值已跌至極具性價比的便宜區間。"
  },
  {
   "symbol": "TSLA",
   "name": "特斯拉",
   "market": "US",
   "stance": "持有中",
   "argument": "財報雖差但馬斯克承諾回歸專注公司是最大利多，長期看好其機器人晶片規劃與 Model Y 改款前景，但目前估值偏高。"
  },
  {
   "symbol": "MSFT",
   "name": "微軟",
   "market": "US",
   "stance": "中性",
   "argument": "AI 支出確實有所放緩，部分算力規劃轉向 Open AI 的 Stargate 專案，市場對此已有預期。"
  },
  {
   "symbol": "GOOG",
   "name": "谷歌",
   "market": "US",
   "stance": "看多",
   "argument": "AI 算力投資健康度最高，自有 TPU 投入不遺餘力且算力供不應求。"
  },
  {
   "symbol": "AMZN",
   "name": "亞馬遜",
   "market": "US",
   "stance": "觀察",
   "argument": "AWS 雖有 CoWoS 調整傳聞，但官方澄清基本面無大礙，需等待法說會進一步確認。"
  }
 ],
 "quotes": [
  "台積電的折舊政策是五年，相較於同業的七到十年更為短痛，這讓它在第六年開始具備極強的成本競爭力。",
  "在市場行情偏空的時候，我們有一個素養，就是盡量避開估值極高、且短期內無法看到大量獲利灌進來的公司。",
  "不要跟馬斯克對賭（Don't bet against Elon），他的注意力放在哪裡，他就會像愚公移山一樣把東西硬幹出來。"
 ],
 "ep_key": "EP551",
 "title": "EP551 | 🐦",
 "pubdate": "2025-04-23",
 "duration_s": 2999
}