{
 "summary": "本集節目中，主持人謝孟恭分享了近期對酒精與生活體驗的體悟，並深入剖析當前瘋狂的市場狀態。他指出，雖然市場熱度極高、融資餘額與開戶數創高，但此波上漲的廣度其實很窄，主要由少數核心科技股（如記憶體、AI 相關股）與大型權值股支撐。他建議投資人應適度降低槓桿、設定移動停利，並將資金轉往估值合理、具備長期趨勢的板塊。此外，他詳細探討了記憶體（NAND Flash/SSD）報價大漲的產業現況，並看好台積電持續擴廠所帶動的半導體廠務、水電、氣體與無塵室等周邊設備商的長期機會。",
 "topics": [
  "生活體悟與酒精成癮者的反思",
  "當前瘋狂市場的風險控管與資金配置策略",
  "記憶體（NAND Flash/SSD）產業報價與合約價趨勢",
  "台積電擴廠效應下的半導體廠務、水電、氣體與無塵室機會",
  "馬斯克兩奈米晶圓廠構想與第一性原理的討論",
  "折疊手機軸承產業趨勢更新"
 ],
 "market_view": "市場有可能瘋狂地超越你的想像，但此波上漲廣度極窄，建議投資人適度降低槓桿、設定移動停利，並將資金轉往估值合理的防守型標的。",
 "industries": [
  {
   "name": "記憶體",
   "stance": "看多",
   "view": "NAND Flash 與 SSD 報價持續瘋狂上漲，原廠漲價態度強硬且不急於鎖定長約價，超級週期尚未結束。"
  },
  {
   "name": "半導體設備與廠務",
   "stance": "看多",
   "view": "台積電持續買地擴廠，將帶動廠務、水電、特殊化學氣體及無塵室（Cleanroom）等周邊需求的長期爆發。"
  },
  {
   "name": "折疊手機軸承",
   "stance": "觀察",
   "view": "蘋果折疊手機開發方向可能轉為對折式（左右折）且僅需單一軸承，相關供應鏈隨消息面起伏。"
  }
 ],
 "tickers": [
  {
   "symbol": "2330",
   "name": "台積電",
   "market": "TW",
   "stance": "持有中",
   "argument": "持續買地擴建新廠，1月中旬法說會的展望將是市場關鍵的檢驗點。"
  },
  {
   "symbol": "AMAT",
   "name": "應用材料",
   "market": "US",
   "stance": "觀察",
   "argument": "美股半導體設備股近期表現極為瘋狂，估值甚至已提前反映到2028年的預期。"
  },
  {
   "symbol": "ASML",
   "name": "艾司摩爾",
   "market": "US",
   "stance": "觀察",
   "argument": "美股半導體設備巨頭之一，近期股價表現強勁但估值偏高。"
  },
  {
   "symbol": "KLA",
   "name": "科磊",
   "market": "US",
   "stance": "觀察",
   "argument": "美股半導體檢測設備龍頭，股價同樣呈現瘋狂噴出的狀態。"
  },
  {
   "symbol": "3081",
   "name": "聯亞",
   "market": "TW",
   "stance": "觀察",
   "argument": "在光通訊與矽光子族群中具備核心地位，但股價一向偏貴且營收尚未完全跟上。"
  },
  {
   "symbol": "3558",
   "name": "神準",
   "market": "TW",
   "stance": "觀察",
   "argument": "聽眾問答提及的光通訊相關個股，主持人列為觀察並提醒注意追高風險。"
  },
  {
   "symbol": "3034",
   "name": "聯詠",
   "market": "TW",
   "stance": "已出場",
   "argument": "主持人已將帳上表現不佳、不隨大盤起舞的標的進行減碼與清倉。"
  },
  {
   "symbol": "8054",
   "name": "安國",
   "market": "TW",
   "stance": "已出場",
   "argument": "先前因消息面狂飆，主持人已在近期逢高獲利了結、清空部位。"
  },
  {
   "symbol": "聖暉*",
   "name": "聖暉*",
   "market": "TW",
   "stance": "看多",
   "argument": "台積電擴廠效應下，無塵室工程與廠務系統整合的直接受益者。"
  },
  {
   "symbol": "信紘科*",
   "name": "信紘科*",
   "market": "TW",
   "stance": "看多",
   "argument": "半導體廠務製程廢液處理及二次配管工程商，受惠於晶圓廠持續擴建。"
  },
  {
   "symbol": "和桐*",
   "name": "和桐*",
   "market": "TW",
   "stance": "看多",
   "argument": "特殊化學品與氣體供應鏈相關，具備二次配管與廠務擴建紅利。"
  },
  {
   "symbol": "兆聯*",
   "name": "兆聯*",
   "market": "TW",
   "stance": "看多",
   "argument": "半導體純水與廢水處理廠務工程商，受惠於台積電全台大擴廠。"
  }
 ],
 "quotes": [
  "當老天親吻了你的舌頭、喉嚨跟腦袋，讓你擁有極佳的味覺與嗅覺，它某個程度上也給你放了一個詛咒，因為你日常的開銷與挑剔會讓你過得很痛苦。",
  "指數的位置其實是靠極少數的股票去把它堆上去的。你現在去射飛鏢亂買，其實是不會賺錢的。",
  "你不用為了喝牛奶去養一頭牛。陪伴才是小孩最需要的，而不是你給他多好的玩具，你卻不在身邊。"
 ],
 "ep_key": "EP626",
 "title": "EP626 | 🕷️",
 "pubdate": "2026-01-10",
 "duration_s": 2999
}