{
 "summary": "本集節目指出台股指數已創歷史新高，證實了主持人先前對修正結束的判斷。當前市場由AI伺服器需求驅動，特別是功率半導體產業，因歐美大廠交期過長，產生「排擠效應」使台灣二、三線供應商受惠。主持人強調，儘管頂級需求仍集中於歐美韓IDM，但產能瓶頸使台灣廠商獲得認證與出貨機會。同時，消費性與車用電子市場的疲軟，反而抑制了整體通膨，讓AI產業的成長得以持續。主持人也分享了在林口投資在地小生意的經驗，強調尋找有決心且願意投入的團隊。對於AI對軟體工程師的影響，他認為這是一個轉型而非淘汰，工程師將從重複性工作轉向更高層次的產品設計與問題解決，AI將作為生產力工具。整體投資策略應著重於觀察市場現象、適應變化，並專注於創造價值，而非預測未來。",
 "topics": [
  "台灣股市與總經展望",
  "功率半導體產業分析",
  "AI伺服器需求與供應鏈",
  "消費性及車用電子市場現況",
  "在地小型企業投資策略",
  "AI對軟體工程師職涯的影響",
  "投資哲學與市場輪動",
  "個人生活與健康議題"
 ],
 "market_view": "台灣股市指數已創歷史新高，顯示先前的修正已結束，市場應以正向態度看待。",
 "industries": [
  {
   "name": "半導體",
   "stance": "看多",
   "view": "AI伺服器需求帶動功率半導體產業，歐美大廠交期過長使台灣供應商受惠，產能是關鍵瓶頸。"
  },
  {
   "name": "AI伺服器",
   "stance": "看多",
   "view": "作為當前市場成長的主要驅動力，對特定零組件產生巨大需求，並帶動整個功率半導體供應鏈。"
  },
  {
   "name": "消費性電子",
   "stance": "看空",
   "view": "市場表現疲軟，但這反而有助於抑制通膨，讓AI產業的成長得以持續而不致過熱。"
  },
  {
   "name": "車用電子",
   "stance": "看空",
   "view": "與消費性電子類似，市場表現不佳，有助於維持整體經濟的穩定，避免AI帶來的過度通膨。"
  },
  {
   "name": "被動元件",
   "stance": "觀察",
   "view": "部分大型被動元件表現強勁，但市場關注點已轉移，部分領域出現震盪。"
  },
  {
   "name": "機器人",
   "stance": "觀察",
   "view": "仍處於萌芽階段，部分工業零件廠商的機器人相關營收有所增加，但需等待更實質的營收獲利驗證。"
  },
  {
   "name": "生技股",
   "stance": "觀察",
   "view": "主持人表示不甚了解，認為許多公司缺乏營收獲利卻股價飆漲，屬於高風險的「深水區」投資。"
  }
 ],
 "tickers": [
  {
   "symbol": "德州儀器",
   "name": "德州儀器",
   "market": "US",
   "stance": "觀察",
   "argument": "作為IDM大廠，其功率半導體產品交期長，是市場需求旺盛的指標之一。"
  },
  {
   "symbol": "STM",
   "name": "意法半導體",
   "market": "other",
   "stance": "觀察",
   "argument": "作為IDM大廠，其功率半導體產品交期長，是市場需求旺盛的指標之一。"
  },
  {
   "symbol": "安森美",
   "name": "安森美",
   "market": "US",
   "stance": "觀察",
   "argument": "作為IDM大廠，其功率半導體產品交期長，是市場需求旺盛的指標之一。"
  },
  {
   "symbol": "國巨",
   "name": "國巨",
   "market": "TW",
   "stance": "觀察",
   "argument": "大型被動元件公司，儘管市場關注點轉移，但仍表現強勁。"
  },
  {
   "symbol": "蒙恬",
   "name": "蒙恬",
   "market": "TW",
   "stance": "觀察",
   "argument": "聽眾提及的股票，近期有顯著漲幅，但主持人未明確分析其基本面。"
  },
  {
   "symbol": "MRVL",
   "name": "Marvell",
   "market": "US",
   "stance": "看多",
   "argument": "主持人曾買入並意外獲得高報酬，顯示其在特定時期有強勁表現。"
  }
 ],
 "quotes": [
  "你只要一直去追求說，要看誰準不準什麼的，你就注定要當韭菜給人家割，因為真的沒有人知道明天會發生什麼事情。大家都是在見招拆招。",
  "當一個東西已經正式的表態，然後開始一堆的媽法人衝進去的時候，就是所有的研究力量都在這邊。所以如果它是假貨的話，它會在未來的一陣子立刻就A下來。",
  "對我們來講，反正這個錢在市場裡面滾絕對是最快的啦，但如果說有一點餘裕可以稍微的去推一下在地的一些發展。"
 ],
 "ep_key": "EP672",
 "title": "EP672 | 🐣",
 "pubdate": "2026-06-20",
 "duration_s": 3205
}